tornado_jsonrpc2/__init__.py
tornado_jsonrpc2/exceptions.py
tornado_jsonrpc2/handler.py
tornado_jsonrpc2/jsonrpc.py
tornado_jsonrpc2-0.5.dist-info/LICENSE
tornado_jsonrpc2-0.5.dist-info/METADATA
tornado_jsonrpc2-0.5.dist-info/WHEEL
tornado_jsonrpc2-0.5.dist-info/top_level.txt
tornado_jsonrpc2-0.5.dist-info/RECORD
