Metadata-Version: 2.1
Name: tornado-jsonrpc2
Version: 0.5
Summary: JSON-RPC request handler for Tornado.
Home-page: https://github.com/okin/tornado-jsonrpc2
Author: Niko Wenselowski
Author-email: niko@nerdno.de
License: UNKNOWN
Project-URL: Source, https://github.com/okin/tornado-jsonrpc2
Keywords: tornado jsonrpc jsonrpc2 rpc json requesthandler
Platform: UNKNOWN
Classifier: Development Status :: 4 - Beta
Classifier: Intended Audience :: Developers
Classifier: License :: OSI Approved :: GNU Affero General Public License v3
Classifier: Operating System :: OS Independent
Classifier: Programming Language :: Python :: 3
Classifier: Programming Language :: Python :: 3.6
Classifier: Programming Language :: Python :: 3.7
Classifier: Programming Language :: Python :: 3 :: Only
Requires-Python: >=3.6
Requires-Dist: tornado (>=5.0)
Provides-Extra: test
Requires-Dist: pytest-tornado (>=0.7) ; extra == 'test'
